<?xml version="1.0" encoding="UTF-8"?>

<!DOCTYPE hibernate-mapping PUBLIC
  "-//Hibernate/Hibernate Mapping DTD 3.0//EN"
  "http://hibernate.sourceforge.net/hibernate-mapping-3.0.dtd">

<hibernate-mapping package="com.mili.onlineShopping.model">

	<class name="Product" table="PRODUCT">
		<id name="productId" type="java.lang.Integer" column="PRODUCT_ID">
			<generator class="identity" />
		</id>
		<property name="code" type="string" column="CODE"/>
		<property name="brand" type="string" column="BRAND"/>
		<property name="description" type="string" column="DESCRIPTION"/>
		<property name="unitPrice" type="double" column="UNIT_PRICE"/>
		<property name="qty" type="java.lang.Integer" column="QTY"/>
		<property name="active" type="boolean" column="IS_ACTIVE"/>
		<many-to-one name="category" column="CATEGORY_ID" unique="false"/>
		<many-to-one name="userDetail" column="USER_ID" unique="false"/>
	</class>
</hibernate-mapping>